collective.mustread-2.2.1-py3.10-nspkg.pth
collective/mustread/__init__.py
collective/mustread/configure.zcml
collective/mustread/db.py
collective/mustread/interfaces.py
collective/mustread/models.py
collective/mustread/setuphandlers.py
collective/mustread/td.py
collective/mustread/testing.py
collective/mustread/tracker.py
collective/mustread/utils.py
collective/mustread/behaviors/__init__.py
collective/mustread/behaviors/configure.zcml
collective/mustread/behaviors/maybe.py
collective/mustread/behaviors/track.py
collective/mustread/browser/__init__.py
collective/mustread/browser/configure.zcml
collective/mustread/browser/init_db.py
collective/mustread/browser/views.py
collective/mustread/locales/collective.mustread.pot
collective/mustread/locales/update.sh
collective/mustread/profiles/default/browserlayer.xml
collective/mustread/profiles/default/metadata.xml
collective/mustread/profiles/default/registry.xml
collective/mustread/profiles/uninstall/browserlayer.xml
collective/mustread/tests/__init__.py
collective/mustread/tests/test_behaviors.py
collective/mustread/tests/test_hit.py
collective/mustread/tests/test_robot.py
collective/mustread/tests/test_setup.py
collective/mustread/tests/test_tracker.py
collective/mustread/tests/test_upgrades.py
collective/mustread/tests/robot/test_example.robot
collective/mustread/upgrades/__init__.py
collective/mustread/upgrades/configure.zcml
collective/mustread/upgrades/to1001.py
collective/mustread/upgrades/to1002.py
collective.mustread-2.2.1.dist-info/METADATA
collective.mustread-2.2.1.dist-info/WHEEL
collective.mustread-2.2.1.dist-info/entry_points.txt
collective.mustread-2.2.1.dist-info/namespace_packages.txt
collective.mustread-2.2.1.dist-info/top_level.txt
collective.mustread-2.2.1.dist-info/RECORD
