Metadata-Version: 2.1
Name: collective.mustread
Version: 2.2.1
Summary: Tracking user views on content items marked as must-read
Home-page: https://pypi.org/project/collective.mustread/
Author: Guido A.J. Stevens
Author-email: guido.stevens@cosent.net
License: GPL version 2
Keywords: Python Plone
Classifier: Environment :: Web Environment
Classifier: Framework :: Plone
Classifier: Framework :: Plone :: Addon
Classifier: Framework :: Plone :: 5.1
Classifier: Framework :: Plone :: 5.2
Classifier: Programming Language :: Python
Classifier: Programming Language :: Python :: 2.7
Classifier: Programming Language :: Python :: 3.6
Classifier: Programming Language :: Python :: 3.7
Classifier: Programming Language :: Python :: 3.8
Classifier: Operating System :: OS Independent
Classifier: License :: OSI Approved :: GNU General Public License v2 (GPLv2)
Requires-Dist: plone.api
Requires-Dist: plone.behavior
Requires-Dist: Products.GenericSetup (>=1.8.2)
Requires-Dist: setuptools
Requires-Dist: sqlalchemy
Requires-Dist: zope.schema
Requires-Dist: zope.interface
Requires-Dist: zope.component
Provides-Extra: test
Requires-Dist: plone.app.testing ; extra == 'test'
Requires-Dist: plone.app.contenttypes ; extra == 'test'
Requires-Dist: plone.app.robotframework[debug,reload] ; extra == 'test'
